{
 "categories": [],
 "equivalent": [],
 "manufacturer": "Turnigy",
 "name": "Aerodrive SK3 - 3530-1150kv Brushless Outrunner Motor",
 "subpart": [],
 "urls": {
  "manufacturer": [],
  "related": []
 },
 "variants": [
  {
   "location": "International Warehouse",
   "price": "$24.80",
   "stock_state": "in_stock",
   "stock_text": "10+",
   "timestamp": "Mon, 28 Sep 2015 01:12:01 GMT",
   "url": "http://www.hobbyking.com/hobbyking/store/__18160__Turnigy_Aerodrive_SK3_3530_1150kv_Brushless_Outrunner_Motor.html"
  },
  {
   "location": "European Warehouse",
   "price": "$28.55",
   "stock_state": "in_stock",
   "stock_text": "10+",
   "timestamp": "Mon, 28 Sep 2015 01:10:30 GMT",
   "url": "http://www.hobbyking.com/hobbyking/store/uh_viewItem.asp?idProduct=37259"
  },
  {
   "location": "Australia Warehouse",
   "price": "$25.95",
   "stock_state": "out_of_stock",
   "stock_text": "0",
   "timestamp": "Mon, 28 Sep 2015 01:10:29 GMT",
   "url": "http://www.hobbyking.com/hobbyking/store/uh_viewItem.asp?idProduct=37609"
  },
  {
   "location": "USA West Warehouse",
   "price": "$25.49",
   "stock_state": "in_stock",
   "stock_text": "10+",
   "timestamp": "Mon, 28 Sep 2015 01:10:28 GMT",
   "url": "http://www.hobbyking.com/hobbyking/store/uh_viewItem.asp?idProduct=37820"
  },
  {
   "location": "UK Warehouse",
   "price": "$26.35",
   "stock_state": "in_stock",
   "stock_text": "10+",
   "timestamp": "Mon, 28 Sep 2015 01:10:27 GMT",
   "url": "http://www.hobbyking.com/hobbyking/store/uh_viewItem.asp?idProduct=38043"
  },
  {
   "location": "USA East Warehouse",
   "price": "$25.49",
   "stock_state": "in_stock",
   "stock_text": "10+",
   "timestamp": "Mon, 28 Sep 2015 01:10:26 GMT",
   "url": "http://www.hobbyking.com/hobbyking/store/uh_viewItem.asp?idProduct=71838"
  }
 ],
 "version": 2,
 "weight": "76"
}