{
 "categories": [],
 "equivalent": [],
 "manufacturer": "Turnigy",
 "name": "Aerodrive SK3 - 2826-1240kv Brushless Outrunner Motor",
 "subpart": [],
 "urls": {
  "manufacturer": [],
  "related": []
 },
 "variants": [
  {
   "location": "International Warehouse",
   "price": "$17.65",
   "stock_state": "in_stock",
   "stock_text": "10+",
   "timestamp": "Mon, 28 Sep 2015 01:05:57 GMT",
   "url": "http://www.hobbyking.com/hobbyking/store/__18115__Turnigy_Aerodrive_SK3_2826_1240kv_Brushless_Outrunner_Motor.html"
  },
  {
   "location": "USA West Warehouse",
   "price": "$17.85",
   "stock_state": "in_stock",
   "stock_text": "10+",
   "timestamp": "Mon, 28 Sep 2015 01:04:08 GMT",
   "url": "http://www.hobbyking.com/hobbyking/store/uh_viewItem.asp?idProduct=28502"
  },
  {
   "location": "UK Warehouse",
   "price": "$18.80",
   "stock_state": "in_stock",
   "stock_text": "10+",
   "timestamp": "Mon, 28 Sep 2015 01:04:06 GMT",
   "url": "http://www.hobbyking.com/hobbyking/store/uh_viewItem.asp?idProduct=29508"
  },
  {
   "location": "Australia Warehouse",
   "price": "$18.20",
   "stock_state": "in_stock",
   "stock_text": "10+",
   "timestamp": "Mon, 28 Sep 2015 01:04:05 GMT",
   "url": "http://www.hobbyking.com/hobbyking/store/uh_viewItem.asp?idProduct=38575"
  },
  {
   "location": "European Warehouse",
   "price": "$18.85",
   "stock_state": "in_stock",
   "stock_text": "10+",
   "timestamp": "Mon, 28 Sep 2015 01:04:05 GMT",
   "url": "http://www.hobbyking.com/hobbyking/store/uh_viewItem.asp?idProduct=39312"
  },
  {
   "location": "Russia Warehouse",
   "price": "$22.98",
   "stock_state": "in_stock",
   "stock_text": "1",
   "timestamp": "Mon, 28 Sep 2015 01:04:04 GMT",
   "url": "http://www.hobbyking.com/hobbyking/store/uh_viewItem.asp?idProduct=69058"
  },
  {
   "location": "USA East Warehouse",
   "price": "$17.85",
   "stock_state": "in_stock",
   "stock_text": "10+",
   "timestamp": "Mon, 28 Sep 2015 01:04:03 GMT",
   "url": "http://www.hobbyking.com/hobbyking/store/uh_viewItem.asp?idProduct=70973"
  }
 ],
 "version": 2,
 "weight": "45"
}