{
 "categories": [],
 "equivalent": [],
 "manufacturer": "Turnigy",
 "name": "Heavy Duty 4000mAh 3S 60C Lipo Pack",
 "replacement": [],
 "subpart": [],
 "urls": {
  "manufacturer": [],
  "related": []
 },
 "variants": [
  {
   "location": "International Warehouse",
   "price": "$32.28",
   "stock_state": "in_stock",
   "stock_text": "10+",
   "timestamp": "Mon, 28 Sep 2015 02:50:17 GMT",
   "url": "http://www.hobbyking.com/hobbyking/store/__53689__Turnigy_Heavy_Duty_4000mAh_3S_60C_Lipo_Pack.html"
  },
  {
   "location": "European Warehouse",
   "price": "$34.97",
   "stock_state": "in_stock",
   "stock_text": "10+",
   "timestamp": "Mon, 28 Sep 2015 02:49:25 GMT",
   "url": "http://www.hobbyking.com/hobbyking/store/uh_viewItem.asp?idProduct=58113"
  },
  {
   "location": "UK Warehouse",
   "price": "$34.17",
   "stock_state": "in_stock",
   "stock_text": "10+",
   "timestamp": "Mon, 28 Sep 2015 02:49:24 GMT",
   "url": "http://www.hobbyking.com/hobbyking/store/uh_viewItem.asp?idProduct=63076"
  },
  {
   "location": "Australia Warehouse",
   "price": "$34.56",
   "stock_state": "in_stock",
   "stock_text": "10+",
   "timestamp": "Mon, 28 Sep 2015 02:49:24 GMT",
   "url": "http://www.hobbyking.com/hobbyking/store/uh_viewItem.asp?idProduct=63773"
  },
  {
   "location": "USA West Warehouse",
   "price": "$33.63",
   "stock_state": "in_stock",
   "stock_text": "10+",
   "timestamp": "Mon, 28 Sep 2015 02:49:22 GMT",
   "url": "http://www.hobbyking.com/hobbyking/store/uh_viewItem.asp?idProduct=64220"
  }
 ],
 "version": 2,
 "weight": "371"
}