{
 "category": "battery",
 "equivalent": [],
 "manufacturer": "Turnigy",
 "name": "nano-tech 450mAh 3S 65C Lipo (E-flite Compatible Blade 180CFX EFLB4503SJ30)",
 "replacement": [],
 "subpart": [],
 "urls": {
  "manufacturer": [],
  "related": [],
  "store": [
   "http://www.hobbyking.com/hobbyking/store/uh_viewItem.asp?idProduct=75759",
   "http://www.hobbyking.com/hobbyking/store/uh_viewItem.asp?idProduct=75758",
   "http://www.hobbyking.com/hobbyking/store/uh_viewItem.asp?idProduct=75757",
   "http://www.hobbyking.com/hobbyking/store/uh_viewItem.asp?idProduct=75756",
   "http://www.hobbyking.com/hobbyking/store/__64210__Turnigy_nano_tech_450mAh_3S_65C_Lipo_E_flite_Compatible_Blade_180CFX_EFLB4503SJ30_.html"
  ]
 }
}