{
 "category": "battery",
 "equivalent": [],
 "manufacturer": "Turnigy",
 "name": "nano-tech 5000mah 10S 25~50C Lipo Pack",
 "replacement": [],
 "subpart": [],
 "urls": {
  "manufacturer": [],
  "related": [],
  "store": [
   "http://www.hobbyking.com/hobbyking/store/uh_viewItem.asp?idProduct=14609",
   "http://www.hobbyking.com/hobbyking/store/__20679__Turnigy_nano_tech_5000mah_10S_25_50C_Lipo_Pack_US_Warehouse_.html",
   "http://www.hobbyking.com/hobbyking/store/uh_viewItem.asp?idProduct=20679",
   "http://www.hobbyking.com/hobbyking/store/__14609__Turnigy_nano_tech_5000mah_10S_25_50C_Lipo_Pack.html"
  ]
 }
}