{
 "categories": [
  "battery"
 ],
 "equivalent": [],
 "manufacturer": "Turnigy",
 "name": "nano-tech 1000mah 2S 20~40C Lipo AIRSOFT Pack",
 "replacement": [],
 "subpart": [],
 "urls": {
  "manufacturer": [],
  "related": []
 },
 "variants": [
  {
   "location": "International Warehouse",
   "price": "$6.70",
   "stock_state": "in_stock",
   "stock_text": "10+",
   "timestamp": "Mon, 28 Sep 2015 03:13:03 GMT",
   "url": "http://www.hobbyking.com/hobbyking/store/__34530__Turnigy_nano_tech_1000mah_2S_20_40C_Lipo_AIRSOFT_Pack.html"
  },
  {
   "location": "USA West Warehouse",
   "price": "$6.85",
   "stock_state": "out_of_stock",
   "stock_text": "0",
   "timestamp": "Mon, 28 Sep 2015 03:12:44 GMT",
   "url": "http://www.hobbyking.com/hobbyking/store/uh_viewItem.asp?idProduct=44070"
  },
  {
   "location": "European Warehouse",
   "price": "$7.55",
   "stock_state": "in_stock",
   "stock_text": "10+",
   "timestamp": "Mon, 28 Sep 2015 03:12:43 GMT",
   "url": "http://www.hobbyking.com/hobbyking/store/uh_viewItem.asp?idProduct=44711"
  },
  {
   "location": "USA East Warehouse",
   "price": "$6.85",
   "stock_state": "in_stock",
   "stock_text": "10+",
   "timestamp": "Mon, 28 Sep 2015 03:12:42 GMT",
   "url": "http://www.hobbyking.com/hobbyking/store/uh_viewItem.asp?idProduct=59276"
  },
  {
   "location": "Russia Warehouse",
   "price": "$8.40",
   "stock_state": "in_stock",
   "stock_text": "10+",
   "timestamp": "Mon, 28 Sep 2015 03:12:40 GMT",
   "url": "http://www.hobbyking.com/hobbyking/store/uh_viewItem.asp?idProduct=60238"
  }
 ],
 "version": 2,
 "weight": "51"
}