{
 "categories": [
  "battery"
 ],
 "equivalent": [],
 "manufacturer": "Turnigy",
 "name": "nano-tech 950mah 1S 25~50C Lipo Pack (Fits Walkera V120, X100)",
 "replacement": [],
 "subpart": [],
 "urls": {
  "manufacturer": [],
  "related": []
 },
 "variants": [
  {
   "location": "International Warehouse",
   "price": "$5.02",
   "stock_state": "in_stock",
   "stock_text": "10+",
   "url": "http://www.hobbyking.com/hobbyking/store/__20387__Turnigy_nano_tech_950mah_1S_25_50C_Lipo_Pack_Walkera_V120_X100_.html"
  },
  {
   "location": "European Warehouse",
   "price": "$4.03",
   "stock_state": "in_stock",
   "stock_text": "10+",
   "url": "http://www.hobbyking.com/hobbyking/store/uh_viewItem.asp?idProduct=32779"
  },
  {
   "location": "USA West Warehouse",
   "price": "$4.05",
   "stock_state": "out_of_stock",
   "stock_text": "0",
   "url": "http://www.hobbyking.com/hobbyking/store/uh_viewItem.asp?idProduct=33258"
  },
  {
   "location": "UK Warehouse",
   "price": "$4.05",
   "stock_state": "in_stock",
   "stock_text": "1",
   "url": "http://www.hobbyking.com/hobbyking/store/uh_viewItem.asp?idProduct=34873"
  },
  {
   "location": "Australia Warehouse",
   "price": "$3.99",
   "stock_state": "out_of_stock",
   "stock_text": "0",
   "url": "http://www.hobbyking.com/hobbyking/store/uh_viewItem.asp?idProduct=35538"
  },
  {
   "location": "USA East Warehouse",
   "price": "$4.05",
   "stock_state": "out_of_stock",
   "stock_text": "0",
   "url": "http://www.hobbyking.com/hobbyking/store/uh_viewItem.asp?idProduct=59076"
  },
  {
   "location": "Russia Warehouse",
   "price": "$5.11",
   "stock_state": "out_of_stock",
   "stock_text": "0",
   "url": "http://www.hobbyking.com/hobbyking/store/uh_viewItem.asp?idProduct=60017"
  }
 ],
 "version": 2,
 "weight": "25"
}