{
 "categories": [],
 "equivalent": [],
 "manufacturer": "Turnigy",
 "name": "TGY-SM-3317MR 360\u00b0 Analog Metal Gear Robot Servo 2.2kg / 78RPM / 26g",
 "replacement": [],
 "subpart": [],
 "urls": {
  "manufacturer": [],
  "related": []
 },
 "variants": [
  {
   "location": "International Warehouse",
   "price": "$11.19",
   "stock_state": "out_of_stock",
   "stock_text": "0",
   "url": "http://www.hobbyking.com/hobbyking/store/__41208__Turnigy_TGY_SM_3317MR_360_Analog_Metal_Gear_Robot_Servo_2_2kg_78RPM_26g.html"
  }
 ],
 "version": 2,
 "weight": "26"
}