{
 "categories": [],
 "equivalent": [],
 "manufacturer": "Turnigy",
 "name": "XK2858-3400KV Brushless Inrunner",
 "replacement": [],
 "subpart": [],
 "urls": {
  "manufacturer": [],
  "related": []
 },
 "variants": [
  {
   "location": "International Warehouse",
   "price": "$21.04",
   "stock_state": "out_of_stock",
   "stock_text": "0",
   "timestamp": "Mon, 28 Sep 2015 00:47:34 GMT",
   "url": "http://www.hobbyking.com/hobbyking/store/__75390__Turnigy_XK2858_3400KV_Brushless_Inrunner.html"
  }
 ],
 "version": 2,
 "weight": "160"
}