{
 "categories": [],
 "equivalent": [],
 "manufacturer": "Turnigy",
 "name": "\u2122 MX-A801 Micro Servo  1.8kg / 0.10sec /8.5g",
 "replacement": [],
 "subpart": [],
 "urls": {
  "manufacturer": [],
  "related": []
 },
 "variants": [
  {
   "location": "International Warehouse",
   "price": "$4.02",
   "stock_state": "in_stock",
   "stock_text": "10+",
   "url": "http://www.hobbyking.com/hobbyking/store/__47378__Turnigy_8482_MX_A801_Micro_Servo_1_8kg_0_10sec_8_5g.html"
  }
 ],
 "version": 2,
 "weight": "8.5"
}