{
 "category": "motor",
 "equivalent": [],
 "manufacturer": "T-Motor",
 "name": "MN2206 2000kv",
 "replacement": [],
 "subpart": [],
 "urls": {
  "manufacturer": [],
  "related": [],
  "store": [
   "http://www.readymaderc.com/store/index.php?main_page=product_info&products_id=2498",
   "http://rotorgeeks.com/index.php?route=product%2Fproduct&product_id=292",
   "http://www.dronematters.com/power-system/brushless-motors/tiger-motor-mn2206-2000kv.html",
   "http://flyduino.net/Multikopter-Brushless-Motor-Multicopter-Navigator-Series_8",
   "http://flyduino.net/Brushless-Motor-Multicopter-T-Motor-Navigator-MN2206-2000KV"
  ]
 }
}
