{
 "categories": [],
 "equivalent": [],
 "manufacturer": "RCX",
 "name": "20A Sky (Linear BEC) Brushless ESC for Aircraft and Heli (2-4S)",
 "replacement": [],
 "subpart": [],
 "urls": {
  "manufacturer": [],
  "related": []
 },
 "variants": [
  {
   "price": "USD5.99",
   "stock_state": "in_stock",
   "stock_text": "Usually ship within 48 hours (Estimated)",
   "url": "http://www.myrcmart.com/rcx-20a-sky-linear-bec-brushless-esc-for-aircraft-and-heli-24s-p-8040.html"
  }
 ],
 "version": 2,
 "weight": "30g"
}