{
 "categories": [],
 "equivalent": [],
 "manufacturer": "RCX",
 "name": "CNC Upgrade Metal Rotor Head Set (Red / Walkera Super CP / Mini CP / Genius CP / Genius CP V2)",
 "replacement": [],
 "subpart": [],
 "urls": {
  "manufacturer": [],
  "related": []
 },
 "variants": [
  {
   "price": "USD14.99",
   "stock_state": "out_of_stock",
   "stock_text": "Time is unforeseen",
   "timestamp": "Sun, 27 Sep 2015 22:30:00 GMT",
   "url": "http://www.myrcmart.com/product_info.php?products_id=5942"
  }
 ],
 "version": 2,
 "weight": "20g"
}