{
 "categories": [],
 "equivalent": [],
 "manufacturer": "RCX",
 "name": "High Quality Canopy for Trex 450 Sport V2 (Glass Fiber / Hand-Painting)",
 "replacement": [],
 "subpart": [],
 "urls": {
  "manufacturer": [],
  "related": []
 },
 "variants": [
  {
   "price": "USD7.99",
   "stock_state": "backordered",
   "stock_text": "Usually ship within 2-5 business days (Estimated)",
   "timestamp": "Sat, 03 Oct 2015 03:35:50 GMT",
   "url": "http://www.myrcmart.com/rcx-high-quality-canopy-for-trex-450-sport-v2-glass-fiber-handpainting-p-5703.html"
  },
  {
   "price": "USD7.99",
   "stock_state": "backordered",
   "stock_text": "Usually ship within 2-5 business days (Estimated)",
   "timestamp": "Sat, 03 Oct 2015 03:35:07 GMT",
   "url": "http://www.myrcmart.com/rcx-high-quality-canopy-for-trex-450-sport-v2-glass-fiber-handpainting-p-5704.html"
  }
 ],
 "version": 2,
 "weight": "100g"
}