{
 "categories": [],
 "equivalent": [],
 "manufacturer": "HJ Toys",
 "name": "HJ-998-06 - Tail Set (B Side / Black & White / Clockwise / White LED)",
 "replacement": [],
 "subpart": [],
 "urls": {
  "manufacturer": [],
  "related": []
 },
 "variants": [
  {
   "price": "USD2.99",
   "stock_state": "in_stock",
   "stock_text": "Usually ship within 48 hours (Estimated)",
   "timestamp": "Sat, 03 Oct 2015 03:41:20 GMT",
   "url": "http://www.myrcmart.com/hj99806-tail-set-side-black-white-clockwise-white-led-p-5728.html"
  }
 ],
 "version": 2,
 "weight": "50g"
}