{
 "category": "",
 "equivalent": [],
 "manufacturer": "",
 "name": "4mm Gold Connectors - Low Profile (10pc)",
 "replacement": [],
 "subpart": [],
 "urls": {
  "manufacturer": [],
  "related": [],
  "store": [
   "http://www.hobbyking.com/hobbyking/store/uh_viewItem.asp?idProduct=64754",
   "http://www.hobbyking.com/hobbyking/store/uh_viewItem.asp?idProduct=47088",
   "http://www.hobbyking.com/hobbyking/store/uh_viewItem.asp?idProduct=46613",
   "http://www.hobbyking.com/hobbyking/store/uh_viewItem.asp?idProduct=42619",
   "http://www.hobbyking.com/hobbyking/store/uh_viewItem.asp?idProduct=42605",
   "http://www.hobbyking.com/hobbyking/store/__25175__4mm_Gold_Connectors_Low_Profile_10pc_.html"
  ]
 }
}