{
 "categories": [],
 "equivalent": [],
 "manufacturer": "",
 "name": "Canopy Thumb Screw (red) (4pcs) for all 30-90 canopy",
 "replacement": [],
 "subpart": [],
 "urls": {
  "manufacturer": [],
  "related": []
 },
 "variants": [
  {
   "location": "International Warehouse",
   "price": "$1.53",
   "stock_state": "out_of_stock",
   "stock_text": "0",
   "timestamp": "Sun, 27 Sep 2015 23:22:15 GMT",
   "url": "http://www.hobbyking.com/hobbyking/store/__12285__Canopy_Thumb_Screw_red_4pcs_for_all_30_90_canopy.html"
  }
 ],
 "version": 2,
 "weight": ""
}