{
 "categories": [],
 "equivalent": [],
 "manufacturer": "",
 "name": "Female EC3 ",
 "subpart": [],
 "urls": {
  "manufacturer": [],
  "related": []
 },
 "variants": [
  {
   "location": "International Warehouse",
   "price": "$4.69",
   "stock_state": "in_stock",
   "stock_text": "10+",
   "url": "http://www.hobbyking.com/hobbyking/store/__10259__Female_EC3_gt_Male_XT60_3pcs_bag_.html"
  },
  {
   "location": "European Warehouse",
   "price": "$3.98",
   "stock_state": "in_stock",
   "stock_text": "10+",
   "url": "http://www.hobbyking.com/hobbyking/store/uh_viewItem.asp?idProduct=36279"
  },
  {
   "location": "Australia Warehouse",
   "price": "$3.83",
   "stock_state": "in_stock",
   "stock_text": "10+",
   "url": "http://www.hobbyking.com/hobbyking/store/uh_viewItem.asp?idProduct=52242"
  },
  {
   "location": "UK Warehouse",
   "price": "$4.25",
   "stock_state": "in_stock",
   "stock_text": "10+",
   "url": "http://www.hobbyking.com/hobbyking/store/uh_viewItem.asp?idProduct=54909"
  },
  {
   "location": "USA West Warehouse",
   "price": "$3.86",
   "stock_state": "in_stock",
   "stock_text": "10+",
   "url": "http://www.hobbyking.com/hobbyking/store/uh_viewItem.asp?idProduct=65718"
  }
 ],
 "version": 2,
 "weight": ""
}