{
 "categories": [],
 "equivalent": [],
 "manufacturer": "",
 "name": "Female Mini Tamiya ",
 "subpart": [],
 "urls": {
  "manufacturer": [],
  "related": []
 },
 "variants": [
  {
   "location": "International Warehouse",
   "price": "$3.15",
   "stock_state": "in_stock",
   "stock_text": "10+",
   "timestamp": "Mon, 28 Sep 2015 02:05:58 GMT",
   "url": "http://www.hobbyking.com/hobbyking/store/__10263__Female_Mini_Tamiya_gt_Male_XT60_3pcs_bag_.html"
  },
  {
   "location": "UK Warehouse",
   "price": "$3.73",
   "stock_state": "in_stock",
   "stock_text": "10+",
   "timestamp": "Mon, 28 Sep 2015 02:04:07 GMT",
   "url": "http://www.hobbyking.com/hobbyking/store/uh_viewItem.asp?idProduct=26048"
  },
  {
   "location": "USA West Warehouse",
   "price": "$3.36",
   "stock_state": "in_stock",
   "stock_text": "10+",
   "timestamp": "Mon, 28 Sep 2015 02:04:06 GMT",
   "url": "http://www.hobbyking.com/hobbyking/store/uh_viewItem.asp?idProduct=30666"
  },
  {
   "location": "European Warehouse",
   "price": "$3.65",
   "stock_state": "in_stock",
   "stock_text": "10+",
   "timestamp": "Mon, 28 Sep 2015 02:04:05 GMT",
   "url": "http://www.hobbyking.com/hobbyking/store/uh_viewItem.asp?idProduct=31472"
  },
  {
   "location": "Australia Warehouse",
   "price": "$3.47",
   "stock_state": "out_of_stock",
   "stock_text": "0",
   "timestamp": "Mon, 28 Sep 2015 02:04:04 GMT",
   "url": "http://www.hobbyking.com/hobbyking/store/uh_viewItem.asp?idProduct=45984"
  },
  {
   "location": "USA East Warehouse",
   "price": "$3.36",
   "stock_state": "in_stock",
   "stock_text": "10+",
   "timestamp": "Mon, 28 Sep 2015 02:04:03 GMT",
   "url": "http://www.hobbyking.com/hobbyking/store/uh_viewItem.asp?idProduct=70473"
  }
 ],
 "version": 2,
 "weight": ""
}