{
 "categories": [],
 "equivalent": [],
 "manufacturer": "",
 "name": "HD2613-1900KV Indoor/Profile/F3P Outrunner Motor",
 "subpart": [],
 "urls": {
  "manufacturer": [],
  "related": []
 },
 "variants": [
  {
   "location": "International Warehouse",
   "price": "$13.99",
   "stock_state": "in_stock",
   "stock_text": "10+",
   "timestamp": "Mon, 28 Sep 2015 01:00:06 GMT",
   "url": "http://www.hobbyking.com/hobbyking/store/__21872__HD2613_1900KV_Indoor_Profile_F3P_Outrunner_Motor.html"
  },
  {
   "location": "USA West Warehouse",
   "price": "$14.40",
   "stock_state": "in_stock",
   "stock_text": "10+",
   "timestamp": "Mon, 28 Sep 2015 00:58:16 GMT",
   "url": "http://www.hobbyking.com/hobbyking/store/uh_viewItem.asp?idProduct=30705"
  },
  {
   "location": "USA East Warehouse",
   "price": "$14.40",
   "stock_state": "in_stock",
   "stock_text": "10+",
   "timestamp": "Mon, 28 Sep 2015 00:58:15 GMT",
   "url": "http://www.hobbyking.com/hobbyking/store/uh_viewItem.asp?idProduct=70693"
  }
 ],
 "version": 2,
 "weight": "25.4"
}