{
 "categories": [],
 "equivalent": [],
 "manufacturer": "",
 "name": "Hummingbirds CH05XL 8000kv Brushless Motor (Blade 130X Upgrade)",
 "subpart": [],
 "urls": {
  "manufacturer": [],
  "related": []
 },
 "variants": [
  {
   "location": "International Warehouse",
   "price": "$25.99",
   "stock_state": "in_stock",
   "stock_text": "8",
   "timestamp": "Mon, 28 Sep 2015 00:59:04 GMT",
   "url": "http://www.hobbyking.com/hobbyking/store/__40698__Hummingbirds_CH05XL_8000kv_Brushless_Motor_Blade_130X_Upgrade_.html"
  }
 ],
 "version": 2,
 "weight": "5.8"
}