{
 "categories": [],
 "equivalent": [],
 "manufacturer": "",
 "name": "TrackStar\u2122 TS-920 Digital 1/10 SCT/4WD Buggy Steering Servo 66g / 13.1kg / 0.07",
 "replacement": [],
 "subpart": [],
 "urls": {
  "manufacturer": [],
  "related": []
 },
 "variants": [
  {
   "location": "International Warehouse",
   "price": "$40.37",
   "stock_state": "in_stock",
   "stock_text": "10+",
   "url": "http://www.hobbyking.com/hobbyking/store/__43055__TrackStar_8482_TS_920_Digital_1_10_SCT_4WD_Buggy_Steering_Servo_66g_13_1kg_0_07sec.html"
  },
  {
   "location": "UK Warehouse",
   "price": "$38.05",
   "stock_state": "out_of_stock",
   "stock_text": "0",
   "url": "http://www.hobbyking.com/hobbyking/store/uh_viewItem.asp?idProduct=62565"
  },
  {
   "location": "USA West Warehouse",
   "price": "$37.06",
   "stock_state": "in_stock",
   "stock_text": "10+",
   "url": "http://www.hobbyking.com/hobbyking/store/uh_viewItem.asp?idProduct=62685"
  },
  {
   "location": "Australia Warehouse",
   "price": "$37.60",
   "stock_state": "out_of_stock",
   "stock_text": "0",
   "url": "http://www.hobbyking.com/hobbyking/store/uh_viewItem.asp?idProduct=62777"
  },
  {
   "location": "European Warehouse",
   "price": "$40.17",
   "stock_state": "out_of_stock",
   "stock_text": "0",
   "url": "http://www.hobbyking.com/hobbyking/store/uh_viewItem.asp?idProduct=77533"
  }
 ],
 "version": 2,
 "weight": "66"
}