{
 "category": "",
 "equivalent": [],
 "manufacturer": "",
 "name": "XT30 Power Connectors for 30A Continuous Applications  (ESC Side) (5pcs)",
 "replacement": [],
 "subpart": [],
 "urls": {
  "manufacturer": [],
  "related": [],
  "store": [
   "http://www.hobbyking.com/hobbyking/store/uh_viewItem.asp?idProduct=73672",
   "http://www.hobbyking.com/hobbyking/store/uh_viewItem.asp?idProduct=73671",
   "http://www.hobbyking.com/hobbyking/store/uh_viewItem.asp?idProduct=73670",
   "http://www.hobbyking.com/hobbyking/store/uh_viewItem.asp?idProduct=73669",
   "http://www.hobbyking.com/hobbyking/store/uh_viewItem.asp?idProduct=73668",
   "http://www.hobbyking.com/hobbyking/store/__65442__XT30_Power_Connectors_for_30A_Continuous_Applications_ESC_Side_5pcs_.html"
  ]
 }
}