{
 "categories": [],
 "equivalent": [],
 "manufacturer": "HobbyKing",
 "name": "50A ESC 4A UBEC",
 "replacement": [],
 "subpart": [],
 "urls": {
  "manufacturer": [],
  "related": []
 },
 "variants": [
  {
   "location": "International Warehouse",
   "price": "$22.02",
   "stock_state": "in_stock",
   "stock_text": "10+",
   "url": "http://www.hobbyking.com/hobbyking/store/__24563__HobbyKing_50A_ESC_4A_UBEC.html"
  },
  {
   "location": "USA West Warehouse",
   "price": "$20.55",
   "stock_state": "in_stock",
   "stock_text": "10+",
   "url": "http://www.hobbyking.com/hobbyking/store/uh_viewItem.asp?idProduct=35678"
  },
  {
   "location": "Australia Warehouse",
   "price": "$20.50",
   "stock_state": "in_stock",
   "stock_text": "10+",
   "url": "http://www.hobbyking.com/hobbyking/store/uh_viewItem.asp?idProduct=35730"
  },
  {
   "location": "European Warehouse",
   "price": "$21.10",
   "stock_state": "in_stock",
   "stock_text": "10+",
   "url": "http://www.hobbyking.com/hobbyking/store/uh_viewItem.asp?idProduct=36687"
  },
  {
   "location": "UK Warehouse",
   "price": "$21.55",
   "stock_state": "in_stock",
   "stock_text": "10+",
   "url": "http://www.hobbyking.com/hobbyking/store/uh_viewItem.asp?idProduct=36840"
  },
  {
   "location": "Russia Warehouse",
   "price": "$27.28",
   "stock_state": "in_stock",
   "stock_text": "10+",
   "url": "http://www.hobbyking.com/hobbyking/store/uh_viewItem.asp?idProduct=69873"
  },
  {
   "location": "USA East Warehouse",
   "price": "$20.53",
   "stock_state": "in_stock",
   "stock_text": "10+",
   "url": "http://www.hobbyking.com/hobbyking/store/uh_viewItem.asp?idProduct=70572"
  }
 ],
 "version": 2,
 "weight": ""
}