{
 "category": "",
 "equivalent": [],
 "manufacturer": "HobbyKing",
 "name": "6A ESC 0.5A UBEC",
 "replacement": [],
 "subpart": [],
 "urls": {
  "manufacturer": [],
  "related": [],
  "store": [
   "http://www.hobbyking.com/hobbyking/store/uh_viewItem.asp?idProduct=70451",
   "http://www.hobbyking.com/hobbyking/store/uh_viewItem.asp?idProduct=39369",
   "http://www.hobbyking.com/hobbyking/store/uh_viewItem.asp?idProduct=36311",
   "http://www.hobbyking.com/hobbyking/store/uh_viewItem.asp?idProduct=29556",
   "http://www.hobbyking.com/hobbyking/store/uh_viewItem.asp?idProduct=24526",
   "http://www.hobbyking.com/hobbyking/store/__21246__HobbyKing_6A_ESC_0_5A_UBEC.html"
  ]
 }
}