{
 "categories": [],
 "equivalent": [],
 "manufacturer": "HobbyKing",
 "name": "B-Grade 2200mAh 2S 20C Lipoly Battery",
 "replacement": [],
 "subpart": [],
 "urls": {
  "manufacturer": [],
  "related": []
 },
 "variants": [
  {
   "location": "International Warehouse",
   "price": "$16.83",
   "stock_state": "in_stock",
   "stock_text": "10+",
   "url": "http://www.hobbyking.com/hobbyking/store/__18505__B_Grade_5000mAh_2S_30C_Hardcase_Lipoly_Battery.html"
  }
 ],
 "version": 2,
 "weight": "305"
}