{
 "category": "",
 "equivalent": [],
 "manufacturer": "HobbyKing",
 "name": "Fury 3D Aerobatic EPP Airplane 800mm (ARF)",
 "replacement": [],
 "subpart": [],
 "urls": {
  "manufacturer": [],
  "related": [],
  "store": [
   "http://www.hobbyking.com/hobbyking/store/uh_viewItem.asp?idProduct=71291",
   "http://www.hobbyking.com/hobbyking/store/uh_viewItem.asp?idProduct=65089",
   "http://www.hobbyking.com/hobbyking/store/uh_viewItem.asp?idProduct=54437",
   "http://www.hobbyking.com/hobbyking/store/uh_viewItem.asp?idProduct=47894",
   "http://www.hobbyking.com/hobbyking/store/uh_viewItem.asp?idProduct=47785",
   "http://www.hobbyking.com/hobbyking/store/__42244__HobbyKing_Fury_3D_Aerobatic_EPP_Airplane_800mm_ARF_.html"
  ]
 }
}