{
 "categories": [],
 "equivalent": [],
 "manufacturer": "HobbyKing",
 "name": "HK15338 Giant Digital Servo MG 175g / 25kg / 0.21s",
 "replacement": [],
 "subpart": [],
 "urls": {
  "manufacturer": [],
  "related": []
 },
 "variants": [
  {
   "location": "International Warehouse",
   "price": "$19.79",
   "stock_state": "in_stock",
   "stock_text": "10+",
   "url": "http://www.hobbyking.com/hobbyking/store/__23491__HobbyKing_8482_HK15338_Giant_Digital_Servo_MG_175g_25kg_0_21s.html"
  },
  {
   "location": "UK Warehouse",
   "price": "$18.30",
   "stock_state": "out_of_stock",
   "stock_text": "0",
   "url": "http://www.hobbyking.com/hobbyking/store/uh_viewItem.asp?idProduct=29342"
  },
  {
   "location": "USA West Warehouse",
   "price": "$16.16",
   "stock_state": "in_stock",
   "stock_text": "7",
   "url": "http://www.hobbyking.com/hobbyking/store/uh_viewItem.asp?idProduct=42447"
  },
  {
   "location": "Australia Warehouse",
   "price": "$16.40",
   "stock_state": "in_stock",
   "stock_text": "3",
   "url": "http://www.hobbyking.com/hobbyking/store/uh_viewItem.asp?idProduct=49216"
  },
  {
   "location": "Russia Warehouse",
   "price": "$20.48",
   "stock_state": "in_stock",
   "stock_text": "1",
   "url": "http://www.hobbyking.com/hobbyking/store/uh_viewItem.asp?idProduct=69861"
  },
  {
   "location": "USA East Warehouse",
   "price": "$16.16",
   "stock_state": "in_stock",
   "stock_text": "10+",
   "url": "http://www.hobbyking.com/hobbyking/store/uh_viewItem.asp?idProduct=71422"
  }
 ],
 "version": 2,
 "weight": "175"
}