{
 "categories": [],
 "equivalent": [],
 "manufacturer": "Diatone",
 "name": "M3x8 Inner Hexagon Screw Pack 20pcs For RC Multirotors",
 "replacement": [],
 "subpart": [],
 "urls": {
  "manufacturer": [],
  "related": []
 },
 "variants": [
  {
   "location": "USA Warehouse",
   "price": "$3.99",
   "stock_state": "in_stock",
   "stock_text": "Only 12 units,dispatched in 1 business day",
   "url": "http://www.banggood.com/Diatone-M3x8-Inner-Hexagon-Screw-Pack-20pcs-For-RC-Multirotors-p-973477.html"
  }
 ],
 "version": 2,
 "weight": ""
}