{
 "categories": [],
 "equivalent": [],
 "manufacturer": "",
 "name": "QuadRevo Rage 180",
 "subpart": [],
 "urls": {
  "manufacturer": [],
  "related": []
 },
 "variants": [
  {
   "price": "$54.99",
   "stock_state": "in_stock",
   "stock_text": "In stock",
   "url": "http://www.multirotorsuperstore.com/quadrevo-rage-180.html"
  },
  {
   "price": "$54.99",
   "stock_state": "in_stock",
   "stock_text": "In stock",
   "url": "https://www.multirotorsuperstore.com/quadrevo-rage-180.html"
  }
 ],
 "version": 2,
 "weight": ""
}