{
 "categories": [],
 "equivalent": [],
 "manufacturer": "KDS",
 "name": "1139-SD - CF Mounting Plate of Electronics",
 "replacement": [],
 "subpart": [],
 "urls": {
  "manufacturer": [],
  "related": []
 },
 "variants": [
  {
   "price": "USD5.99",
   "stock_state": "in_stock",
   "stock_text": "Usually ship within 48 hours (Estimated)",
   "timestamp": "Sun, 27 Sep 2015 21:58:14 GMT",
   "url": "http://www.myrcmart.com/kds1139sd-cf-mounting-plate-of-electronics-p-4495.html"
  }
 ],
 "version": 2,
 "weight": "30g"
}