{
 "categories": [],
 "equivalent": [],
 "manufacturer": "Walkera",
 "name": "FPV iLook+ HD Camera 1920x1080P 13MP with Build-in Transmitter",
 "replacement": [],
 "subpart": [],
 "urls": {
  "manufacturer": [],
  "related": []
 },
 "variants": [
  {
   "location": "CN Direct",
   "stock_state": "in_stock",
   "stock_text": "Usually dispatched in 6-9 business days",
   "url": "http://www.banggood.com/Walkera-FPV-iLook-HD-Camera-1920x1080P-13MP-with-Buildin-Transmitter-p-928378.html"
  }
 ],
 "version": 2,
 "weight": ""
}