{
 "categories": [],
 "equivalent": [],
 "manufacturer": "Walkera",
 "name": "Screw Set",
 "replacement": [],
 "subpart": [],
 "urls": {
  "manufacturer": [],
  "related": []
 },
 "variants": [
  {
   "price": "USD4.99",
   "stock_state": "in_stock",
   "stock_text": "Usually ship within 48 hours (Estimated)",
   "url": "http://www.myrcmart.com/screw-set-p-8146.html"
  },
  {
   "price": "USD3.49",
   "stock_state": "in_stock",
   "stock_text": "Usually ship within 48 hours (Estimated)",
   "url": "http://www.myrcmart.com/screw-set-p-8170.html"
  },
  {
   "price": "USD3.99",
   "stock_state": "in_stock",
   "stock_text": "Usually ship within 48 hours (Estimated)",
   "url": "http://www.myrcmart.com/screw-set-p-8306.html"
  }
 ],
 "version": 2,
 "weight": "30g"
}