{
 "categories": [],
 "equivalent": [],
 "manufacturer": "FatShark",
 "name": "Fat Shark Earphones with Adjustable Volume Control",
 "replacement": [],
 "subpart": [],
 "urls": {
  "manufacturer": [],
  "related": []
 },
 "variants": [
  {
   "price": "$6.49",
   "stock_state": "in_stock",
   "stock_text": "126 Units in Stock",
   "timestamp": "Sat, 26 Sep 2015 21:41:03 GMT",
   "url": "http://www.readymaderc.com/store/index.php?main_page=product_info&products_id=460"
  }
 ],
 "version": 2,
 "weight": ""
}