{
 "categories": [],
 "equivalent": [],
 "manufacturer": "Eachine",
 "name": "Q200 Combo RCtimer 1306 3100KV Motor EMAX BL12A ESC CC3D 4045 Prope",
 "replacement": [],
 "subpart": [],
 "urls": {
  "manufacturer": [],
  "related": []
 },
 "variants": [
  {
   "location": "CN Warehouse",
   "price": "$105.99",
   "stock_state": "in_stock",
   "stock_text": "In stock, usually dispatched in 1 business day",
   "timestamp": "Sun, 27 Sep 2015 20:57:42 GMT",
   "url": "http://www.banggood.com/Eachine-Q200-Combo-RCtimer-1306-3100KV-Motor-EMAX-BL12A-ESC-CC3D-4045-Prope-p-976300.html"
  }
 ],
 "version": 2,
 "weight": ""
}