{
 "categories": [],
 "equivalent": [],
 "manufacturer": "",
 "name": "6\" G10 Propeller Guards",
 "replacement": [],
 "subpart": [],
 "urls": {
  "manufacturer": [],
  "related": []
 },
 "variants": [
  {
   "price": "US$14.99",
   "stock_state": "in_stock",
   "timestamp": "Sat, 26 Sep 2015 23:34:53 GMT",
   "url": "http://www.dronematters.com/5-g10-propeller-guards-795.html"
  },
  {
   "price": "US$14.99",
   "stock_state": "in_stock",
   "timestamp": "Sat, 26 Sep 2015 23:25:43 GMT",
   "url": "http://www.dronematters.com/5-g10-propeller-guards-796.html"
  },
  {
   "price": "US$14.99",
   "stock_state": "in_stock",
   "timestamp": "Sat, 19 Sep 2015 00:38:35 GMT",
   "url": "http://www.dronematters.com/5-g10-propeller-guards-797.html"
  },
  {
   "price": "US$14.99",
   "stock_state": "in_stock",
   "timestamp": "Sat, 26 Sep 2015 23:36:59 GMT",
   "url": "http://www.dronematters.com/5-g10-propeller-guards-798.html"
  }
 ],
 "version": 2,
 "weight": ""
}