{
 "category": "",
 "equivalent": [],
 "manufacturer": "Zippy",
 "name": "6000mah 2S2P 35C Hardcase Pack",
 "replacement": [],
 "subpart": [],
 "urls": {
  "manufacturer": [],
  "related": [],
  "store": [
   "http://www.hobbyking.com/hobbyking/store/uh_viewItem.asp?idProduct=58722",
   "http://www.hobbyking.com/hobbyking/store/uh_viewItem.asp?idProduct=38345",
   "http://www.hobbyking.com/hobbyking/store/uh_viewItem.asp?idProduct=32231",
   "http://www.hobbyking.com/hobbyking/store/uh_viewItem.asp?idProduct=25275",
   "http://www.hobbyking.com/hobbyking/store/uh_viewItem.asp?idProduct=24195",
   "http://www.hobbyking.com/hobbyking/store/__18610__ZIPPY_6000mah_2S2P_35C_Hardcase_Pack.html"
  ]
 }
}