{
 "category": "",
 "equivalent": [],
 "manufacturer": "Zippy",
 "name": "Compact 3300mAh 6s 60c Lipo Pack",
 "replacement": [],
 "subpart": [],
 "urls": {
  "manufacturer": [],
  "related": [],
  "store": [
   "http://www.hobbyking.com/hobbyking/store/uh_viewItem.asp?idProduct=74538",
   "http://www.hobbyking.com/hobbyking/store/uh_viewItem.asp?idProduct=73826",
   "http://www.hobbyking.com/hobbyking/store/uh_viewItem.asp?idProduct=73749",
   "http://www.hobbyking.com/hobbyking/store/uh_viewItem.asp?idProduct=73406",
   "http://www.hobbyking.com/hobbyking/store/uh_viewItem.asp?idProduct=72475",
   "http://www.hobbyking.com/hobbyking/store/uh_viewItem.asp?idProduct=72356",
   "http://www.hobbyking.com/hobbyking/store/__63402__ZIPPY_Compact_3300mAh_6s_60c_Lipo_Pack.html"
  ]
 }
}