{
 "category": "",
 "equivalent": [],
 "manufacturer": "Zippy",
 "name": "Compact 2700mAh 5S 35C Lipo Pack",
 "replacement": [],
 "subpart": [],
 "urls": {
  "manufacturer": [],
  "related": [],
  "store": [
   "http://www.hobbyking.com/hobbyking/store/uh_viewItem.asp?idProduct=59764",
   "http://www.hobbyking.com/hobbyking/store/uh_viewItem.asp?idProduct=58846",
   "http://www.hobbyking.com/hobbyking/store/uh_viewItem.asp?idProduct=36196",
   "http://www.hobbyking.com/hobbyking/store/uh_viewItem.asp?idProduct=34643",
   "http://www.hobbyking.com/hobbyking/store/uh_viewItem.asp?idProduct=33206",
   "http://www.hobbyking.com/hobbyking/store/uh_viewItem.asp?idProduct=33003",
   "http://www.hobbyking.com/hobbyking/store/__21398__ZIPPY_Compact_2700mAh_5S_35C_Lipo_Pack.html"
  ]
 }
}