{
 "categories": [],
 "equivalent": [],
 "manufacturer": "Zippy",
 "name": "Flightmax 5800mAh 4S1P 30C",
 "replacement": [],
 "subpart": [],
 "urls": {
  "manufacturer": [],
  "related": []
 },
 "variants": [
  {
   "location": "International Warehouse",
   "price": "$73.27",
   "stock_state": "in_stock",
   "stock_text": "10+",
   "url": "http://www.hobbyking.com/hobbyking/store/__9933__ZIPPY_Flightmax_5800mAh_4S1P_30C.html"
  },
  {
   "location": "USA West Warehouse",
   "price": "$57.67",
   "stock_state": "in_stock",
   "stock_text": "10+",
   "url": "http://www.hobbyking.com/hobbyking/store/uh_viewItem.asp?idProduct=16795"
  },
  {
   "location": "Australia Warehouse",
   "price": "$57.71",
   "stock_state": "in_stock",
   "stock_text": "10+",
   "url": "http://www.hobbyking.com/hobbyking/store/uh_viewItem.asp?idProduct=19901"
  },
  {
   "location": "UK Warehouse",
   "price": "$58.44",
   "stock_state": "in_stock",
   "stock_text": "10+",
   "url": "http://www.hobbyking.com/hobbyking/store/uh_viewItem.asp?idProduct=32179"
  },
  {
   "location": "European Warehouse",
   "price": "$58.76",
   "stock_state": "in_stock",
   "stock_text": "10+",
   "url": "http://www.hobbyking.com/hobbyking/store/uh_viewItem.asp?idProduct=38244"
  },
  {
   "location": "USA East Warehouse",
   "price": "$57.67",
   "stock_state": "in_stock",
   "stock_text": "10+",
   "url": "http://www.hobbyking.com/hobbyking/store/uh_viewItem.asp?idProduct=58784"
  },
  {
   "location": "Russia Warehouse",
   "price": "$72.50",
   "stock_state": "in_stock",
   "stock_text": "10+",
   "url": "http://www.hobbyking.com/hobbyking/store/uh_viewItem.asp?idProduct=59697"
  }
 ],
 "version": 2,
 "weight": "568"
}