{
 "categories": [],
 "equivalent": [],
 "manufacturer": "Align",
 "name": "H45086 - Carbon Fiber Main Frame/1.2mm",
 "replacement": [],
 "subpart": [],
 "urls": {
  "manufacturer": [],
  "related": []
 },
 "variants": [
  {
   "price": "USD15.29",
   "stock_state": "in_stock",
   "stock_text": "Usually ship within 48 hours (Estimated)",
   "timestamp": "Sat, 03 Oct 2015 04:32:00 GMT",
   "url": "http://www.myrcmart.com/h45086-carbon-fiber-main-frame12mm-p-5565.html"
  }
 ],
 "version": 2,
 "weight": "100g"
}