{
 "categories": [],
 "equivalent": [],
 "manufacturer": "Align",
 "name": "H45141 - Sport V2 Metal Mixing Arm (U)",
 "replacement": [],
 "subpart": [],
 "urls": {
  "manufacturer": [],
  "related": []
 },
 "variants": [
  {
   "price": "USD13.49",
   "stock_state": "in_stock",
   "stock_text": "Usually ship within 48 hours (Estimated)",
   "timestamp": "Sun, 27 Sep 2015 22:13:29 GMT",
   "url": "http://www.myrcmart.com/h45141-sport-v2-metal-mixing-arm-p-5143.html"
  }
 ],
 "version": 2,
 "weight": "10g"
}