{
 "categories": [],
 "equivalent": [],
 "manufacturer": "Align",
 "name": "H60027-1-84 - Metal Aileron Lever/Blue",
 "replacement": [],
 "subpart": [],
 "urls": {
  "manufacturer": [],
  "related": []
 },
 "variants": [
  {
   "price": "USD20.69",
   "stock_state": "in_stock",
   "stock_text": "Usually ship within 48 hours (Estimated)",
   "timestamp": "Sun, 27 Sep 2015 22:07:32 GMT",
   "url": "http://www.myrcmart.com/h60027184-metal-aileron-leverblue-p-7498.html"
  }
 ],
 "version": 2,
 "weight": "40g"
}