{
 "categories": [],
 "equivalent": [],
 "manufacturer": "ImmersionRC",
 "name": " EzUHF Transmitter",
 "replacement": [],
 "subpart": [],
 "urls": {
  "manufacturer": [],
  "related": []
 },
 "variants": [
  {
   "price": "$206.99",
   "stock_state": "in_stock",
   "stock_text": "In Stock",
   "timestamp": "Sat, 26 Sep 2015 01:32:32 GMT",
   "url": "http://www.getfpv.com/immersionrc-ezuhf-transmitter.html"
  },
  {
   "url": "https://www.liftrc.com/immersionrc-ezuhf-transmitter"
  }
 ],
 "version": 2,
 "weight": ""
}