{
 "categories": [
  "prop"
 ],
 "equivalent": [],
 "manufacturer": "HQProp",
 "name": "5x4x3 Direct Drive Carbon Fiber Composite",
 "replacement": [],
 "subpart": [],
 "urls": {
  "manufacturer": [],
  "related": []
 },
 "variants": [
  {
   "url": "http://flyduino.net/HQProp-Triple-Prop-5x4x3-Carbon-reinforced-Propeller-Set-Black-2CW-2-CCW"
  },
  {
   "url": "http://flyduino.net/Multikopter-Propeller-CW-CCW_45"
  },
  {
   "url": "http://flyduino.net/HQProp-Three-Blade-5x4-127cm-Propeller-Set-Black-4-pcs-Carbon-reinforced"
  },
  {
   "price": "$3.32",
   "stock_state": "in_stock",
   "timestamp": "Sat, 26 Sep 2015 06:27:58 GMT",
   "url": "http://www.readytoflyquads.com/hq-prop-5x4x3-carbon-composite-prop"
  },
  {
   "price": "$3.32",
   "stock_state": "backordered",
   "stock_text": "0 Units in Stock",
   "timestamp": "Sat, 26 Sep 2015 22:08:45 GMT",
   "url": "http://www.readymaderc.com/store/index.php?main_page=product_info&products_id=3206"
  },
  {
   "price": "$3.32",
   "stock_state": "in_stock",
   "stock_text": "69 Units in Stock",
   "timestamp": "Sat, 26 Sep 2015 22:08:46 GMT",
   "url": "http://www.readymaderc.com/store/index.php?main_page=product_info&products_id=3207"
  }
 ],
 "version": 2,
 "weight": ""
}