{
 "categories": [],
 "equivalent": [],
 "manufacturer": "HQProp",
 "name": "8\"x4.5 (20.32cm) Propeller Set Black - 4 pcs, Carbon reinforced",
 "replacement": [],
 "subpart": [],
 "urls": {
  "manufacturer": [],
  "related": []
 },
 "variants": [
  {
   "price": "7,80 \u20ac",
   "stock_state": "in_stock",
   "timestamp": "Wed, 30 Sep 2015 19:20:20 GMT",
   "url": "http://flyduino.net/HQProp-8x45-2032cm-Propeller-Set-Black-4-pcs-Carbon-reinforced"
  },
  {
   "price": "7,80 \u20ac",
   "stock_state": "in_stock",
   "timestamp": "Wed, 30 Sep 2015 19:20:19 GMT",
   "url": "http://flyduino.net/HQProp-8x45-2032cm-Propeller-Set-Black-4-pcs-Carbon-reinforced_1"
  }
 ],
 "version": 2,
 "weight": "0,04kg"
}