{
 "categories": [],
 "equivalent": [],
 "manufacturer": "WL Toys",
 "name": "V949 UFO 4CH 2.4Ghz 4-Axis BNF QuadCopter (Red / BNF / Without Transmitter)",
 "replacement": [],
 "subpart": [],
 "urls": {
  "manufacturer": [],
  "related": []
 },
 "variants": [
  {
   "price": "USD24.99",
   "stock_state": "out_of_stock",
   "stock_text": "Time is unforeseen",
   "timestamp": "Sun, 27 Sep 2015 22:41:35 GMT",
   "url": "http://www.myrcmart.com/product_info.php?products_id=5795"
  }
 ],
 "version": 2,
 "weight": "600g"
}