{
 "categories": [],
 "equivalent": [],
 "manufacturer": "WL Toys",
 "name": "WL-L959-04 - Rear Lower Arm",
 "replacement": [],
 "subpart": [],
 "urls": {
  "manufacturer": [],
  "related": []
 },
 "variants": [
  {
   "price": "USD2.49",
   "stock_state": "backordered",
   "stock_text": "Usually ship within 2-5 business days (Estimated)",
   "timestamp": "Sun, 27 Sep 2015 22:00:14 GMT",
   "url": "http://www.myrcmart.com/wll95904-rear-lower-arm-p-6595.html"
  }
 ],
 "version": 2,
 "weight": "30g"
}