{
 "categories": [],
 "equivalent": [],
 "manufacturer": "",
 "name": "2S-6S Lipo Battery Converter Charger For RC Model With Electron",
 "replacement": [],
 "subpart": [],
 "urls": {
  "manufacturer": [],
  "related": []
 },
 "variants": [
  {
   "location": "CN Warehouse",
   "stock_state": "in_stock",
   "stock_text": "Only 10 units,dispatched in 1 business day",
   "url": "http://www.banggood.com/2S-6S-Lipo-Battery-Converter-Charger-For-RC-Model-With-Electron-p-91902.html"
  }
 ],
 "version": 2,
 "weight": ""
}