{
 "categories": [],
 "equivalent": [],
 "manufacturer": "",
 "name": "Fatshark 7.4V 1000mAh Li-Po Battery With Banana Discharge Adapter",
 "replacement": [],
 "subpart": [],
 "urls": {
  "manufacturer": [],
  "related": []
 },
 "variants": [
  {
   "location": "CN Warehouse",
   "price": "$21.99",
   "stock_state": "in_stock",
   "stock_text": "Arriving soon, expected dispatch in 3 days",
   "url": "http://www.banggood.com/FatShark-7_4V-1000mAh-Li-Po-Battery-Pack-With-Banana-Discharge-Adapter-p-915679.html"
  }
 ],
 "version": 2,
 "weight": ""
}