{
 "categories": [],
 "equivalent": [],
 "manufacturer": "",
 "name": "Fatshark Dominator V2 FPV Goggles Video Glasses 600 X 480 VGA",
 "replacement": [],
 "subpart": [],
 "urls": {
  "manufacturer": [],
  "related": []
 },
 "variants": [
  {
   "location": "EU Warehouse",
   "stock_state": "in_stock",
   "stock_text": "Only 40 units,dispatched in 1 business day",
   "url": "http://www.banggood.com/Fat-Shark-DOMINATOR-V2-FPV-Goggles-Video-Glasses-600-X-480-VGA-p-917599.html"
  }
 ],
 "version": 2,
 "weight": ""
}