{
 "categories": [],
 "equivalent": [],
 "manufacturer": "",
 "name": "FCMODEL 1245 12*4.5 CW/CCW Self-locking Propeller Prop For Multicopter",
 "replacement": [],
 "subpart": [],
 "urls": {
  "manufacturer": [],
  "related": []
 },
 "variants": [
  {
   "location": "CN Warehouse",
   "price": "$2.53",
   "stock_state": "in_stock",
   "stock_text": "Usually dispatched in 6-9 business days",
   "timestamp": "Sat, 03 Oct 2015 05:39:31 GMT",
   "url": "http://www.banggood.com/FCMODEL-1245-124_5-CWCCW-Self-locking-Propeller-Prop-For-Multicopter-p-958094.html"
  }
 ],
 "version": 2,
 "weight": ""
}