{
 "categories": [],
 "equivalent": [],
 "manufacturer": "",
 "name": "FX787T 5.8G 200mW 40CH AV Transmitter With DV For FPV Multicopter",
 "subpart": [],
 "urls": {
  "manufacturer": [],
  "related": []
 },
 "variants": [
  {
   "location": "CN Direct",
   "stock_state": "in_stock",
   "stock_text": "Only 24 units,dispatched in 1 business day",
   "url": "http://www.banggood.com/FX787T-5_8G-200mW-40CH-AV-Transmitter-With-DV-For-FPV-Multicopter-p-1009507.html"
  }
 ],
 "version": 2,
 "weight": ""
}