{
 "categories": [],
 "equivalent": [],
 "manufacturer": "",
 "name": "SMA Male to Male Adapter RF Connector Right Angle 90 Degree",
 "replacement": [],
 "subpart": [],
 "urls": {
  "manufacturer": [],
  "related": []
 },
 "variants": [
  {
   "location": "CN Warehouse",
   "stock_state": "in_stock",
   "stock_text": "In stock, usually dispatched in 1 business day",
   "url": "http://www.banggood.com/SMA-Male-to-Male-Adapter-RF-Connector-Right-Angle-90-Degree-p-925210.html"
  }
 ],
 "version": 2,
 "weight": ""
}