{
 "categories": [],
 "equivalent": [],
 "manufacturer": "",
 "name": "X2804 2280KV CW/CCW Brushless Motor &15A ESC & 6045 3-Leaf Nylon Propelle",
 "replacement": [],
 "subpart": [],
 "urls": {
  "manufacturer": [],
  "related": []
 },
 "variants": [
  {
   "location": "CN Warehouse",
   "price": "$65.93",
   "stock_state": "in_stock",
   "stock_text": "Only 1 units,dispatched in 1 business day",
   "url": "http://www.banggood.com/X2804-2280KV-CWCCW-Brushless-Motor-15A-ESC-6045-3-Leaf-Nylon-Propelle-p-979291.html"
  }
 ],
 "version": 2,
 "weight": ""
}