{
 "categories": [],
 "equivalent": [],
 "manufacturer": "Nine Eagles",
 "name": "NE402228014A - Tail Strut Set",
 "replacement": [],
 "subpart": [],
 "urls": {
  "manufacturer": [],
  "related": []
 },
 "variants": [
  {
   "price": "USD5.49",
   "stock_state": "in_stock",
   "stock_text": "Usually ship within 48 hours (Estimated)",
   "timestamp": "Sat, 03 Oct 2015 04:10:24 GMT",
   "url": "http://www.myrcmart.com/ne402228014a-tail-strut-set-p-4526.html"
  }
 ],
 "version": 2,
 "weight": "10g"
}