{
 "categories": [],
 "equivalent": [],
 "manufacturer": "Nine Eagles",
 "name": "NE480075 - Receiver Set (J6 Pro)",
 "replacement": [],
 "subpart": [],
 "urls": {
  "manufacturer": [],
  "related": []
 },
 "variants": [
  {
   "price": "USD29.99",
   "stock_state": "in_stock",
   "stock_text": "Usually ship within 48 hours (Estimated)",
   "timestamp": "Sat, 03 Oct 2015 04:15:13 GMT",
   "url": "http://www.myrcmart.com/ne480075-receiver-set-j6-pro-p-5044.html"
  }
 ],
 "version": 2,
 "weight": "40g"
}